music_util/__init__.py
music_util/icon.png
music_util/main.py
music_util/pipe.py
music_util/transcr.py
music_util/utils.py
music_util/voc_rem.py
music_util-3.0.20.dist-info/METADATA
music_util-3.0.20.dist-info/WHEEL
music_util-3.0.20.dist-info/entry_points.txt
music_util-3.0.20.dist-info/top_level.txt
music_util-3.0.20.dist-info/RECORD
