Metadata-Version: 2.1
Name: music_util
Version: 3.0.20
Summary: Collection of utilities for musicians
Author-email: Maoserr <maoserr@gmail.com>
License: MIT
Project-URL: Bug Reports, https://github.com/maoserr/music-util/issues
Project-URL: Source, https://github.com/maoserr/music-util
Keywords: music, utility
Requires-Python: >=3.7
Requires-Dist: sv-ttk >=2.5.5
Provides-Extra: crepe
Requires-Dist: torchcrepe >=0.0.22 ; extra == 'crepe'
Requires-Dist: librosa >=0.9.1 ; extra == 'crepe'
Requires-Dist: pandas >=2.0.0 ; extra == 'crepe'
Provides-Extra: demucs
Requires-Dist: demucs >=4.0.1 ; extra == 'demucs'
